{
  "version": "7",
  "dialect": "postgresql",
  "entries": [
    {
      "idx": 0,
      "version": "7",
      "when": 1776677955954,
      "tag": "0000_smooth_tyger_tiger",
      "breakpoints": true
    },
    {
      "idx": 1,
      "version": "7",
      "when": 1776795075635,
      "tag": "0001_bizarre_jetstream",
      "breakpoints": true
    },
    {
      "idx": 2,
      "version": "7",
      "when": 1776873320668,
      "tag": "0002_funny_siren",
      "breakpoints": true
    },
    {
      "idx": 3,
      "version": "7",
      "when": 1776904583051,
      "tag": "0003_fluffy_scream",
      "breakpoints": true
    },
    {
      "idx": 4,
      "version": "7",
      "when": 1776908748746,
      "tag": "0004_blue_king_bedlam",
      "breakpoints": true
    }
  ]
}